fiatlux/__init__.py
fiatlux/_core.cpython-313-x86_64-linux-gnu.so
fiatlux.libs/libgfortran-8f1e9814.so.5.0.0
fiatlux.libs/libquadmath-828275a7.so.0.0.0
fiatlux-0.1.5.dist-info/METADATA
fiatlux-0.1.5.dist-info/WHEEL
fiatlux-0.1.5.dist-info/top_level.txt
fiatlux-0.1.5.dist-info/RECORD
fiatlux-0.1.5.dist-info/licenses/LICENSE
