Metadata-Version: 2.4
Name: fiatlux
Version: 0.1.5
Summary: API for LUXqed methodology in global PDF fits
Author: Stefano Carrazza
License: AGPLv3
Requires-Python: >=3.6
License-File: LICENSE
Provides-Extra: test
Requires-Dist: pytest; extra == "test"
Dynamic: author
Dynamic: description
Dynamic: description-content-type
Dynamic: license
Dynamic: license-file
Dynamic: provides-extra
Dynamic: requires-python
Dynamic: summary
